{
  "workspace": {
    "workspaceConfig": "angular.json",
    "workspaceTsConfig": "tsconfig.json",
    "libsFolder": "projects"
  },
  "entities": {
    "smartComponent": {
      "id": "smartComponent",
      "type": "ANGULAR",
      "suffix": "Component",
      "folder": "ui/$name$",
      "insideOf": "App"
    },
    "dataService": {
      "id": "dataService",
      "type": "SERVICE",
      "suffix": "Service",
      "folder": "services",
      "insideOf": "App"
    },
    "model": {
      "id": "model",
      "type": "DATA_STRUCTURE",
      "suffix": "Model",
      "folder": "model",
      "insideOf": "App"
    }
  },
  "entityRelations": {
    "smartComponent": {
      "httpClient": "CONSTRUCTOR",
      "dataService": "CONSTRUCTOR"
    },
    "dataService": {
      "httpClient": "CONSTRUCTOR"
    }
  }
}
